xdsl_jax/__init__.py
xdsl_jax/compiler.py
xdsl_jax/py.typed
xdsl_jax/universe.py
xdsl_jax/dialects/__init__.py
xdsl_jax/dialects/stablehlo.py
xdsl_jax/frontend/__init__.py
xdsl_jax/frontend/jaxpr.py
xdsl_jax/interpreters/__init__.py
xdsl_jax/transforms/__init__.py
xdsl_jax-0.2.0.dist-info/METADATA
xdsl_jax-0.2.0.dist-info/WHEEL
xdsl_jax-0.2.0.dist-info/entry_points.txt
xdsl_jax-0.2.0.dist-info/licenses/LICENSE
xdsl_jax-0.2.0.dist-info/RECORD
