Metadata-Version: 2.4
Name: xdsl-jax
Version: 0.2.0
Summary: Extend JAX with xDSL.
Project-URL: Homepage, https://xdsl.dev/xdsl-jax
Project-URL: Source Code, https://github.com/xdslproject/xdsl-jax
Project-URL: Issue Tracker, https://github.com/xdslproject/xdsl-jax/issues
Author-email: Sasha Lopoukhine <sasha@lopoukhine.com>
License: Apache License v2.0 with LLVM Exceptions
License-File: LICENSE
Classifier: Programming Language :: Python :: 3 :: Only
Classifier: Typing :: Typed
Requires-Python: >=3.10
Requires-Dist: jax>=0.6.2
Requires-Dist: xdsl~=0.56.0
